WFacer/__init__.py
WFacer/convergence.py
WFacer/enumeration.py
WFacer/fit.py
WFacer/jobs.py
WFacer/maker.py
WFacer/preprocessing.py
WFacer/schema.py
WFacer/wrangling.py
WFacer/sample_generators/__init__.py
WFacer/sample_generators/mc_generators.py
WFacer/specie_decorators/__init__.py
WFacer/specie_decorators/base.py
WFacer/specie_decorators/charge.py
WFacer/utils/__init__.py
WFacer/utils/convex_hull.py
WFacer/utils/duplicacy.py
WFacer/utils/occu.py
WFacer/utils/query.py
WFacer/utils/selection.py
WFacer/utils/sparselm_estimators.py
WFacer/utils/supercells.py
WFacer/utils/task_document.py
WFacer-0.0.0.dist-info/LICENSE
WFacer-0.0.0.dist-info/METADATA
WFacer-0.0.0.dist-info/WHEEL
WFacer-0.0.0.dist-info/top_level.txt
WFacer-0.0.0.dist-info/RECORD
