Metadata-Version: 2.1
Name: WFacer
Version: 0.0.0
Summary: An automated workflow for constructing cluster expansion.
Author-email: Fengyu Xie <fengyu_xie@berkeley.edu>
License: BSD 3-Clause License
Classifier: Development Status :: 3 - Alpha
Classifier: Programming Language :: Python :: 3 :: Only
Classifier: Programming Language :: Python :: 3.8
Classifier: Programming Language :: Python :: 3.9
Classifier: Programming Language :: Python :: 3.10
Classifier: Intended Audience :: Science/Research
Classifier: License :: OSI Approved :: BSD License
Classifier: Operating System :: OS Independent
Classifier: Topic :: Scientific/Engineering :: Information Analysis
Classifier: Topic :: Scientific/Engineering :: Mathematics
Classifier: Topic :: Software Development :: Libraries :: Python Modules
Requires-Python: >=3.8
License-File: LICENSE
Requires-Dist: setuptools
Requires-Dist: numpy >=1.23.5
Requires-Dist: pymatgen <2023.9.10,>=2023.8.10
Requires-Dist: monty >=v2023.9.5
Requires-Dist: pyyaml >=6.0
Requires-Dist: joblib >=1.2.0
Requires-Dist: smol >=0.5.1
Requires-Dist: sparse-lm >=0.4.0
Requires-Dist: sympy >=1.11.1
Requires-Dist: jobflow >=0.1.9
Requires-Dist: atomate2 >=0.0.11
Requires-Dist: emmet-core >=0.51.1
Requires-Dist: scikit-learn >=1.2.0
Requires-Dist: scikit-optimize >=0.9.0
Requires-Dist: scipy <=1.10.1,>=1.10.0
Requires-Dist: pydantic <2.0,>=1.10.2
Requires-Dist: polytope >=0.2.3
Requires-Dist: cvxpy >=1.2.1
Requires-Dist: cvxopt
Provides-Extra: dev
Requires-Dist: pre-commit ; extra == 'dev'
Requires-Dist: black ; extra == 'dev'
Requires-Dist: isort ; extra == 'dev'
Requires-Dist: flake8 ; extra == 'dev'
Requires-Dist: pylint ; extra == 'dev'
Requires-Dist: pydocstyle ; extra == 'dev'
Requires-Dist: flake8-pyproject ; extra == 'dev'
Provides-Extra: docs
Requires-Dist: sphinx >=7.0.0 ; extra == 'docs'
Requires-Dist: pydata-sphinx-theme >=0.13.3 ; extra == 'docs'
Requires-Dist: sphinx-copybutton >=0.5.2 ; extra == 'docs'
Requires-Dist: sphinx-autodoc-typehints >=1.24.0 ; extra == 'docs'
Requires-Dist: sphinx-mdinclude ; extra == 'docs'
Provides-Extra: optional
Requires-Dist: gurobipy ; extra == 'optional'
Provides-Extra: tests
Requires-Dist: pytest >=7.2.0 ; extra == 'tests'
Requires-Dist: pytest-cov >=4.0.0 ; extra == 'tests'
Requires-Dist: coverage ; extra == 'tests'
Requires-Dist: gurobipy ; extra == 'tests'
Requires-Dist: pyscipopt >=4.0.0 ; extra == 'tests'
